ini/__init__.py
ini_parser-2.0.1.dist-info/licenses/LICENSE
tests/__init__.py
tests/test_ini.py
ini_parser-2.0.1.dist-info/METADATA
ini_parser-2.0.1.dist-info/WHEEL
ini_parser-2.0.1.dist-info/top_level.txt
ini_parser-2.0.1.dist-info/RECORD
