Metadata-Version: 2.4
Name: ini-parser
Version: 2.0.1
Summary: An ini parser/serializer in Python
Home-page: https://github.com/vrumger/ini-parser
Author: Avrumy Lunger
Author-email: contact@lungers.com
License: MIT
License-File: LICENSE
Dynamic: author
Dynamic: author-email
Dynamic: description
Dynamic: description-content-type
Dynamic: home-page
Dynamic: license
Dynamic: license-file
Dynamic: summary
